PHCMlib/__init__.py
PHCMlib/main.py
PHCMlib-0.1.dist-info/LICENSE
PHCMlib-0.1.dist-info/METADATA
PHCMlib-0.1.dist-info/WHEEL
PHCMlib-0.1.dist-info/top_level.txt
PHCMlib-0.1.dist-info/RECORD
