Metadata-Version: 2.1
Name: PHCMlib
Version: 0.1
Summary: Part of PHCM backend functionality
Home-page: https://gleb.tk/
Author: Gleb Rusyaev
Author-email: gleb@gleb.tk
License: MIT
Platform: UNKNOWN
Classifier: Programming Language :: Python :: 3
Classifier: License :: OSI Approved :: MIT License
Classifier: Operating System :: OS Independent
Requires-Dist: pycryptodome
